factly/validate_dataset/__init__.py
factly/validate_dataset/app_logger.py
factly/validate_dataset/assets/constants.py
factly/validate_dataset/assets/names.py
factly/validate_dataset/checks.py
factly/validate_dataset/cli.py
factly/validate_dataset/engine.py
factly/validate_dataset/models.py
factly/validate_dataset/settings.py
factly/validate_dataset/textwrapper.py
factly/validate_dataset/utils.py
factly_validate_dataset-0.2.1.dist-info/METADATA
factly_validate_dataset-0.2.1.dist-info/WHEEL
factly_validate_dataset-0.2.1.dist-info/entry_points.txt
factly_validate_dataset-0.2.1.dist-info/RECORD
